python_runtime_entity_wrappers.py
python_runtime_entity_wrappers-0.1.0a0.dist-info/licenses/LICENSE
python_runtime_entity_wrappers-0.1.0a0.dist-info/METADATA
python_runtime_entity_wrappers-0.1.0a0.dist-info/WHEEL
python_runtime_entity_wrappers-0.1.0a0.dist-info/top_level.txt
python_runtime_entity_wrappers-0.1.0a0.dist-info/RECORD
