Metadata-Version: 2.4
Name: python-runtime-entity-wrappers
Version: 0.1.0a0
Summary: A set of small classes to represent Python runtime objects - modules, classes, functions, constants, and abstract instances - in a structured and consistent way.
Author-email: Jifeng Wu <jifengwu2k@gmail.com>
License-Expression: MIT
Project-URL: Homepage, https://github.com/jifengwu2k/python-runtime-entity-wrappers
Project-URL: Bug Tracker, https://github.com/jifengwu2k/python-runtime-entity-wrappers/issues
Classifier: Programming Language :: Python :: 2
Classifier: Programming Language :: Python :: 3
Classifier: Operating System :: OS Independent
Requires-Python: >=2
License-File: LICENSE
Requires-Dist: typing; python_version < "3.5"
Dynamic: license-file
